{"_default": {"1": {"name": "MOP", "firstname": "Moppy", "birthdate": "18/04/2000", "id": "AB12345", "ranking": "6", "gender": "M", "points": 4.5}, "2": {"name": "SAD", "firstname": "Saddy", "birthdate": "24/11/2003", "id": "BC32658", "ranking": "2", "gender": "M", "points": 5.5}, "3": {"name": "DAS", "firstname": "Dassy", "birthdate": "05/05/1999", "id": "DE56874", "ranking": "7", "gender": "M", "points": 3.5}, "4": {"name": "GAL", "firstname": "Mally", "birthdate": "12/06/1993", "id": "EF36974", "ranking": "5", "gender": "M", "points": 10.5}, "5": {"name": "QOP", "firstname": "Qoppy", "birthdate": "12/09/1997", "id": "GH57951", "ranking": "4", "gender": "F", "points": 7.5}, "6": {"name": "KEL", "firstname": "Kelly", "birthdate": "25/07/1988", "id": "IJ48635", "ranking": "1", "gender": "F", "points": 7.5}, "7": {"name": "RAG", "firstname": "Ganny", "birthdate": "22/01/2001", "id": "OP52487", "ranking": "3", "gender": "M", "points": 8.5}, "8": {"name": "BONK", "firstname": "Manny", "birthdate": "02/01/1998", "id": "FZ52478", "ranking": "8", "gender": "M", "points": 5.5}}}